thinsos/__init__.py
thinsos/core.py
thinsos/util.py
thinsos/niwa/monthly_met_data.py
thinsos/tests/__init__.py
thinsos/tests/test_sos.py
thinsos-0.1.2.dist-info/METADATA
thinsos-0.1.2.dist-info/WHEEL
thinsos-0.1.2.dist-info/licenses/LICENSE.txt
thinsos-0.1.2.dist-info/RECORD
