Metadata-Version: 2.3
Name: thinsos
Version: 0.1.2
Summary: Python API to the 52North SOS implementation
Project-URL: Documentation, https://github.com/mullenkamp/ThinSOS
Project-URL: Source, https://github.com/mullenkamp/ThinSOS
Author-email: mullenkamp <mullenkamp1@gmail.com>
License-File: LICENSE.txt
Classifier: Programming Language :: Python :: 3 :: Only
Requires-Python: >=3.9
Requires-Dist: pandas
Requires-Dist: requests
